{
  "title": "IMG20241014180605.jpg",
  "description": "",
  "imageViews": "2",
  "creationTime": {
    "timestamp": "1728909390",
    "formatted": "Oct 14, 2024, 12:36:30 PM UTC"
  },
  "photoTakenTime": {
    "timestamp": "1728909365",
    "formatted": "Oct 14, 2024, 12:36:05 PM UTC"
  },
  "geoData": {
    "latitude": 21.747587199999998,
    "longitude": 72.0967407,
    "altitude": 0.0,
    "latitudeSpan": 0.0,
    "longitudeSpan": 0.0
  },
  "geoDataExif": {
    "latitude": 21.747587199999998,
    "longitude": 72.0967407,
    "altitude": 0.0,
    "latitudeSpan": 0.0,
    "longitudeSpan": 0.0
  },
  "people": [{
    "name": "Mummy"
  }],
  "url": "https://photos.google.com/photo/AF1QipP858EbFbVGsz8NVERsiKzXwwzEa0DBqCwNDBln",
  "googlePhotosOrigin": {
    "mobileUpload": {
      "deviceFolder": {
        "localFolderName": ""
      },
      "deviceType": "ANDROID_PHONE"
    }
  },
  "appSource": {
    "androidPackageName": "com.oplus.camera"
  }
}