{
  "title": "IMG20241125155915.jpg",
  "description": "",
  "imageViews": "1",
  "creationTime": {
    "timestamp": "1732530592",
    "formatted": "Nov 25, 2024, 10:29:52 AM UTC"
  },
  "photoTakenTime": {
    "timestamp": "1732530555",
    "formatted": "Nov 25, 2024, 10:29:15 AM UTC"
  },
  "geoData": {
    "latitude": 22.3299198,
    "longitude": 70.7952957,
    "altitude": 79.0,
    "latitudeSpan": 0.0,
    "longitudeSpan": 0.0
  },
  "geoDataExif": {
    "latitude": 22.3299198,
    "longitude": 70.7952957,
    "altitude": 79.0,
    "latitudeSpan": 0.0,
    "longitudeSpan": 0.0
  },
  "url": "https://photos.google.com/photo/AF1QipMJ2uu9ZFGOUIVhnxP0hBUbnzr9j1NBv3-MrYSE",
  "googlePhotosOrigin": {
    "mobileUpload": {
      "deviceFolder": {
        "localFolderName": ""
      },
      "deviceType": "ANDROID_PHONE"
    }
  },
  "appSource": {
    "androidPackageName": "com.oplus.camera"
  }
}