{
  "title": "IMG20241004092934.jpg",
  "description": "",
  "imageViews": "1",
  "creationTime": {
    "timestamp": "1728054173",
    "formatted": "Oct 4, 2024, 3:02:53 PM UTC"
  },
  "photoTakenTime": {
    "timestamp": "1728014374",
    "formatted": "Oct 4, 2024, 3:59:34 AM UTC"
  },
  "geoData": {
    "latitude": 0.0,
    "longitude": 0.0,
    "altitude": 0.0,
    "latitudeSpan": 0.0,
    "longitudeSpan": 0.0
  },
  "geoDataExif": {
    "latitude": 0.0,
    "longitude": 0.0,
    "altitude": 0.0,
    "latitudeSpan": 0.0,
    "longitudeSpan": 0.0
  },
  "people": [{
    "name": "Me"
  }],
  "url": "https://photos.google.com/photo/AF1QipMGHlN6DwW5E3aXVLjydvby3MhAvpuHrbVRcQRI",
  "googlePhotosOrigin": {
    "mobileUpload": {
      "deviceFolder": {
        "localFolderName": "AdobeLightroom"
      },
      "deviceType": "ANDROID_PHONE"
    }
  },
  "appSource": {
    "androidPackageName": "com.adobe.lrmobile"
  }
}