{
  "title": "IMG20241003223831.jpg",
  "description": "",
  "imageViews": "2",
  "creationTime": {
    "timestamp": "1727975332",
    "formatted": "Oct 3, 2024, 5:08:52 PM UTC"
  },
  "photoTakenTime": {
    "timestamp": "1727975311",
    "formatted": "Oct 3, 2024, 5:08:31 PM UTC"
  },
  "geoData": {
    "latitude": 22.328844099999998,
    "longitude": 70.7944794,
    "altitude": 80.0,
    "latitudeSpan": 0.0,
    "longitudeSpan": 0.0
  },
  "geoDataExif": {
    "latitude": 22.328844099999998,
    "longitude": 70.7944794,
    "altitude": 80.0,
    "latitudeSpan": 0.0,
    "longitudeSpan": 0.0
  },
  "people": [{
    "name": "Me"
  }],
  "url": "https://photos.google.com/photo/AF1QipOExsxApBLjuR4PG4qRTZB8jMCL1q65mKSa3P0Y",
  "googlePhotosOrigin": {
    "mobileUpload": {
      "deviceFolder": {
        "localFolderName": ""
      },
      "deviceType": "ANDROID_PHONE"
    }
  },
  "appSource": {
    "androidPackageName": "com.oplus.camera"
  }
}