{
  "title": "IMG_0756.PNG",
  "description": "",
  "imageViews": "1",
  "creationTime": {
    "timestamp": "1734319415",
    "formatted": "Dec 16, 2024, 3:23:35 AM UTC"
  },
  "photoTakenTime": {
    "timestamp": "1734318276",
    "formatted": "Dec 16, 2024, 3:04:36 AM UTC"
  },
  "geoData": {
    "latitude": 0.0,
    "longitude": 0.0,
    "altitude": 0.0,
    "latitudeSpan": 0.0,
    "longitudeSpan": 0.0
  },
  "geoDataExif": {
    "latitude": 0.0,
    "longitude": 0.0,
    "altitude": 0.0,
    "latitudeSpan": 0.0,
    "longitudeSpan": 0.0
  },
  "url": "https://photos.google.com/photo/AF1QipPpa5dupw8wV4EU__yaSN72SXp6blFbwMPW4hZw",
  "googlePhotosOrigin": {
    "mobileUpload": {
      "deviceType": "IOS_PHONE"
    }
  }
}