{
  "title": "IMG_0774.JPG",
  "description": "",
  "imageViews": "1",
  "creationTime": {
    "timestamp": "1734329298",
    "formatted": "Dec 16, 2024, 6:08:18 AM UTC"
  },
  "photoTakenTime": {
    "timestamp": "1734329115",
    "formatted": "Dec 16, 2024, 6:05:15 AM UTC"
  },
  "geoData": {
    "latitude": 22.2457139,
    "longitude": 70.7080944,
    "altitude": 0.0,
    "latitudeSpan": 0.0,
    "longitudeSpan": 0.0
  },
  "geoDataExif": {
    "latitude": 22.2457139,
    "longitude": 70.7080944,
    "altitude": 0.0,
    "latitudeSpan": 0.0,
    "longitudeSpan": 0.0
  },
  "people": [{
    "name": "Me"
  }],
  "url": "https://photos.google.com/photo/AF1QipP1h0Lhpa5eGBtA3uw4FlzPNA6l-9xak7LHul1f",
  "googlePhotosOrigin": {
    "mobileUpload": {
      "deviceType": "IOS_PHONE"
    }
  }
}