{
  "title": "IMG_0215.HEIC",
  "description": "",
  "imageViews": "3",
  "creationTime": {
    "timestamp": "1733399303",
    "formatted": "Dec 5, 2024, 11:48:23 AM UTC"
  },
  "photoTakenTime": {
    "timestamp": "1733397411",
    "formatted": "Dec 5, 2024, 11:16:51 AM UTC"
  },
  "geoData": {
    "latitude": 21.7457611,
    "longitude": 72.09776389999999,
    "altitude": 33.865718842068276,
    "latitudeSpan": 0.0,
    "longitudeSpan": 0.0
  },
  "geoDataExif": {
    "latitude": 21.7457611,
    "longitude": 72.09776389999999,
    "altitude": 33.865718842068276,
    "latitudeSpan": 0.0,
    "longitudeSpan": 0.0
  },
  "people": [{
    "name": "Me"
  }],
  "url": "https://photos.google.com/photo/AF1QipPgiO9ucJnzChfAls21p6Sia2rsQejC0tbFx8Ft",
  "googlePhotosOrigin": {
    "mobileUpload": {
      "deviceType": "IOS_PHONE"
    }
  }
}