{
  "title": "IMG_0177.HEIC",
  "description": "",
  "imageViews": "1",
  "creationTime": {
    "timestamp": "1733392930",
    "formatted": "Dec 5, 2024, 10:02:10 AM UTC"
  },
  "photoTakenTime": {
    "timestamp": "1733389426",
    "formatted": "Dec 5, 2024, 9:03:46 AM UTC"
  },
  "geoData": {
    "latitude": 21.746277799999998,
    "longitude": 72.0979917,
    "altitude": 31.253251721499616,
    "latitudeSpan": 0.0,
    "longitudeSpan": 0.0
  },
  "geoDataExif": {
    "latitude": 21.746277799999998,
    "longitude": 72.0979917,
    "altitude": 31.253251721499616,
    "latitudeSpan": 0.0,
    "longitudeSpan": 0.0
  },
  "people": [{
    "name": "Me"
  }],
  "url": "https://photos.google.com/photo/AF1QipNBh_Z1q6531wIM9mcZYxaYhkWB1RToI4IGrp7B",
  "googlePhotosOrigin": {
    "mobileUpload": {
      "deviceType": "IOS_PHONE"
    }
  }
}