{
  "title": "IMG_0202.HEIC",
  "description": "",
  "imageViews": "5",
  "creationTime": {
    "timestamp": "1733393293",
    "formatted": "Dec 5, 2024, 10:08:13 AM UTC"
  },
  "photoTakenTime": {
    "timestamp": "1733393161",
    "formatted": "Dec 5, 2024, 10:06:01 AM UTC"
  },
  "geoData": {
    "latitude": 21.7463139,
    "longitude": 72.09805279999999,
    "altitude": 31.157039640695178,
    "latitudeSpan": 0.0,
    "longitudeSpan": 0.0
  },
  "geoDataExif": {
    "latitude": 21.7463139,
    "longitude": 72.09805279999999,
    "altitude": 31.157039640695178,
    "latitudeSpan": 0.0,
    "longitudeSpan": 0.0
  },
  "url": "https://photos.google.com/photo/AF1QipMJ2Hm72n3UHikbOL4Yj6EYwZTtpc7gY6WvJhJW",
  "googlePhotosOrigin": {
    "mobileUpload": {
      "deviceType": "IOS_PHONE"
    }
  }
}